checkio_json_serializer/__init__.py
checkio_json_serializer-0.2.4.dist-info/LICENSE
checkio_json_serializer-0.2.4.dist-info/METADATA
checkio_json_serializer-0.2.4.dist-info/WHEEL
checkio_json_serializer-0.2.4.dist-info/top_level.txt
checkio_json_serializer-0.2.4.dist-info/RECORD
