Metadata-Version: 2.1
Name: checkio-json-serializer
Version: 0.2.4
Summary: JSON serilizer for more complex objects
Home-page: https://github.com/CheckiO/checkio-json-serializer
Author: CheckiO
Author-email: a.lyabah@checkio.org
License: UNKNOWN
Platform: UNKNOWN
Classifier: Programming Language :: Python :: 3
Classifier: License :: OSI Approved :: MIT License
Classifier: Operating System :: OS Independent
Requires-Python: >=3.5
License-File: LICENSE
